src/featstore/__init__.py
src/featstore/example.py
featstore_nightly-0.0.1.dist-info/METADATA
featstore_nightly-0.0.1.dist-info/WHEEL
featstore_nightly-0.0.1.dist-info/licenses/LICENSE
featstore_nightly-0.0.1.dist-info/RECORD
